{
    "KPlugin": {
        "Authors": [
            {
                "Email": "henrique.pinto@kdemail.net", 
                "Name": "Henrique Pinto"
            }
        ], 
        "Id": "kerfuffle_libarchive_readonly", 
        "License": "BSD", 
        "MimeTypes": [
            "application/x-deb", 
            "application/x-cd-image", 
            "application/x-bcpio", 
            "application/x-cpio", 
            "application/x-cpio-compressed", 
            "application/x-sv4cpio", 
            "application/x-sv4crc", 
            "application/x-rpm", 
            "application/x-source-rpm", 
            "application/vnd.ms-cab-compressed"
        ], 
        "Name": "kerfuffle_libarchive_readonly", 
        "ServiceTypes": [
            "Kerfuffle/Plugin"
        ], 
        "Version": "0.0.1", 
        "Website": "http://www.kde.org"
    }, 
    "X-KDE-Kerfuffle-APIRevision": 1, 
    "X-KDE-Kerfuffle-ReadWrite": false, 
    "X-KDE-Priority": 100
}